basketball_reference_scraper/__init__.py
basketball_reference_scraper/box_scores.py
basketball_reference_scraper/br_names.txt
basketball_reference_scraper/constants.py
basketball_reference_scraper/drafts.py
basketball_reference_scraper/injury_report.py
basketball_reference_scraper/lookup.py
basketball_reference_scraper/pbp.py
basketball_reference_scraper/players.py
basketball_reference_scraper/request_utils.py
basketball_reference_scraper/seasons.py
basketball_reference_scraper/shot_charts.py
basketball_reference_scraper/teams.py
basketball_reference_scraper/utils.py
test/__init__.py
test/test_box_scores.py
test/test_drafts.py
test/test_injury_report.py
test/test_pbp.py
test/test_players.py
test/test_seasons.py
test/test_shot_charts.py
test/test_teams.py
basketball_reference_scraper-2.0.0.dist-info/LICENSE
basketball_reference_scraper-2.0.0.dist-info/METADATA
basketball_reference_scraper-2.0.0.dist-info/WHEEL
basketball_reference_scraper-2.0.0.dist-info/top_level.txt
basketball_reference_scraper-2.0.0.dist-info/RECORD
