Metadata-Version: 2.1
Name: basketball_reference_scraper
Version: 2.0.0
Summary: A Python client for scraping stats and data from Basketball Reference
Home-page: https://github.com/vishaalagartha/basketball_reference_scraper
Author: Vishaal Agartha
Author-email: vishaalagartha@gmail.com
License: MIT
Keywords: nba,sports,data mining,basketball,basketball reference,basketball-reference.com
Classifier: Programming Language :: Python :: 3
Classifier: License :: OSI Approved :: MIT License
Classifier: Operating System :: OS Independent
Requires-Python: >=3.6
License-File: LICENSE
Requires-Dist: beautifulsoup4
Requires-Dist: bs4
Requires-Dist: lxml
Requires-Dist: numpy
Requires-Dist: pandas
Requires-Dist: python-dateutil
Requires-Dist: pytz
Requires-Dist: requests
Requires-Dist: six
Requires-Dist: soupsieve
Requires-Dist: Unidecode
Requires-Dist: selenium
Provides-Extra: test
Requires-Dist: unittest; extra == "test"
